asyncfm/__init__.py
asyncfm/api/__init__.py
asyncfm/api/user.py
asyncfm/exceptions.py
asyncfm/types.py
asyncfm/utils.py
async_fm-0.0.7.dist-info/LICENSE
async_fm-0.0.7.dist-info/METADATA
async_fm-0.0.7.dist-info/WHEEL
async_fm-0.0.7.dist-info/RECORD
