Metadata-Version: 2.1
Name: Async-FM
Version: 0.0.7
Summary: Python library for interacting with the Last.fm API asynchronously.
Home-page: https://github.com/NachABR/async-fm
License: MIT
Keywords: python,lastfm,aiohttp,async
Author: NachABR
Author-email: nachabr@protonmail.com
Requires-Python: >=3.10,<4.0
Classifier: License :: OSI Approved :: MIT License
Classifier: Programming Language :: Python :: 3
Classifier: Programming Language :: Python :: 3.10
Classifier: Programming Language :: Python :: 3.11
Classifier: Programming Language :: Python :: 3.12
Classifier: Programming Language :: Python :: 3.13
Requires-Dist: aiohttp (>=3.10.0,<4.0.0)
Requires-Dist: pydantic (>=2.0.0,<3.0.0)
Project-URL: Repository, https://github.com/NachABR/async-fm.git
